GraphDash-0.11.1.data/scripts/GraphDashManage
graphdash/__init__.py
graphdash/__main__.py
graphdash/_version.py
graphdash/defaults.py
graphdash/flask_utils.py
graphdash/load.py
graphdash/markdown_filter.py
graphdash/nlp.py
graphdash/routes.py
graphdash/assets/css/theme_dark.css
graphdash/assets/css/theme_dark.css.map
graphdash/assets/css/theme_light.css
graphdash/assets/css/theme_light.css.map
graphdash/assets/img/bars.ico
graphdash/assets/img/graph.ico
graphdash/assets/img/org.ico
graphdash/assets/img/tree.ico
graphdash/assets/js/family.js
graphdash/assets/js/family.js.map
graphdash/assets/js/family.min.js
graphdash/assets/js/family.min.js.map
graphdash/assets/js/index.js
graphdash/assets/js/index.js.map
graphdash/assets/js/index.min.js
graphdash/assets/js/index.min.js.map
graphdash/struct/__init__.py
graphdash/struct/defaulttransformdict.py
graphdash/struct/semifrozendict.py
graphdash/struct/transformdict.py
graphdash/struct/tree.py
graphdash/templates/404.html
graphdash/templates/base.html
graphdash/templates/family.html
graphdash/templates/index.html
graphdash/templates/macros.html
GraphDash-0.11.1.dist-info/LICENSE
GraphDash-0.11.1.dist-info/METADATA
GraphDash-0.11.1.dist-info/WHEEL
GraphDash-0.11.1.dist-info/entry_points.txt
GraphDash-0.11.1.dist-info/top_level.txt
GraphDash-0.11.1.dist-info/RECORD
