Metadata-Version: 2.1
Name: GraphDash
Version: 0.11.1
Summary: A web-based dashboard built from graphs and their metadata
Home-page: https://github.com/AmadeusITGroup/graphdash
Author: Alex Prengère
Author-email: alex.prengere@amadeus.com
License: UNKNOWN
Platform: UNKNOWN
Classifier: Development Status :: 5 - Production/Stable
Classifier: Programming Language :: Python :: 3
Classifier: Programming Language :: Python :: 3 :: Only
Classifier: Programming Language :: Python :: Implementation :: CPython
Classifier: Programming Language :: Python :: Implementation :: PyPy
Requires-Python: >=3.6.1
License-File: LICENSE
Requires-Dist: PyYAML
Requires-Dist: Flask
Requires-Dist: Markdown
Requires-Dist: Pygments
Requires-Dist: stop-words
